gitgen/__init__.py
gitgen/cli.py
gitgen-0.1.6.dist-info/LICENSE
gitgen-0.1.6.dist-info/METADATA
gitgen-0.1.6.dist-info/WHEEL
gitgen-0.1.6.dist-info/entry_points.txt
gitgen-0.1.6.dist-info/top_level.txt
gitgen-0.1.6.dist-info/RECORD
