Metadata-Version: 2.1
Name: gitgen
Version: 0.1.6
Summary: A simple tool to generate git commits to boost GitHub activity
Home-page: https://github.com/mubashardev/gitgen
Author: Mubashar Hussain
Author-email: hello@mubashar.dev
Classifier: Programming Language :: Python :: 3
Classifier: License :: OSI Approved :: MIT License
Classifier: Operating System :: OS Independent
Requires-Python: >=3.6
License-File: LICENSE
